V_primo_elab/Or.v
module Or(
	input A, B,
	output reg O
);

	always @(A, B) begin
		O = A | B;
	end
	
endmodule

V_primo_elab/And.v
module And #(parameter N = 8)(
	input [N-1:0] A, input [N-1:0] B,
	output reg [N-1:0] O
	);
	integer i;
	always @(A, B) begin
		for(i = 0; i < N; i = i + 1) begin
			O[i] = A[i] & B[i];
		end
	end
endmodule

V_primo_elab/Not.v
module Not #(parameter N = 8)(
	input [N-1:0] A,
	output reg [N-1:0] O
	);
	integer i;
	always @(A) begin
		for(i = 0; i < N; i = i + 1) begin
			O[i] = ~A[i];
		end
	end
endmodule

V_primo_elab/Xnor.v
module Xnor(
    input A, B,
    output reg O
);
	
	
	always @(A, B) begin
		O = A ~^ B;
	end
	
endmodule

V_primo_elab/comparatore_minoranza.v
module comp_min(
	input [2:0] str1, str2,
	output O
);

	wire nn1, xx1, aa1, nn2, xx2, aa2, nn3, aa3, aa4, aa5, oo1, aa6;
	
	Not #(1) N1(
		.A(str1[2]),
		.O(nn1)	
	);
	
	Xnor X1(
		.A(str1[2]),
		.B(str2[2]),
		.O(xx1)
	);
	
	
	And #(1) A1(
		.A(nn1),
		.B(str2[2]),
		.O(aa1)
	);
	
	
	
	
	Not #(1) N2(
		.A(str1[1]),
		.O(nn2)	
	);
	
	Xnor X2(
		.A(str1[1]),
		.B(str2[1]),
		.O(xx2)
	);
	
	
	And #(1) A2(
		.A(nn2),
		.B(str2[1]),
		.O(aa2)
	);
	
	
	
	
	Not #(1) N3(
		.A(str1[0]),
		.O(nn3)	
	);
	
	
	And #(1) A3(
		.A(nn3),
		.B(str2[0]),
		.O(aa3)
	);
	
	
	
	
	And #(1) A4(
		.A(xx1),
		.B(aa2),
		.O(aa4)
	);
	
	
	And #(1) A5(
		.A(xx1),
		.B(xx2),
		.O(aa5)
	);
	
	
	
	
	Or O1(
		.A(aa1),
		.B(aa4),
		.O(oo1)
	);
	
	
	And #(1) A6(
		.A(aa5),
		.B(aa3),
		.O(aa6)
	);
	
	
	
	
	Or O2(
		.A(oo1),
		.B(aa6),
		.O(O)
	);
	
endmodule

V_primo_elab/comparatore_minoranza_tb.v
module tb_comp_min;

    reg [2:0] str1;
    reg [2:0] str2;
    wire O;

    integer i, j;

    comp_min uut (
        .str1(str1),
        .str2(str2),
        .O(O)
    );

    initial begin
        str1 = 3'b000;
        str2 = 3'b000;

	$dumpfile("comp_min.vcd");
	$dumpvars(0, tb_comp_min);

        for (i = 0; i < 8; i = i + 1) begin
            for (j = 0; j < 8; j = j + 1) begin
                str1 = i[2:0];   // FIX
                str2 = j[2:0];   // FIX
                #10;
            end
        end

        $finish;
    end

endmodule

V_primo_elab/comp_min.vcd
$version Generated by VerilatedVcd $end
$timescale 1ps $end
 $scope module TOP $end
  $scope module tb_comp_min $end
   $var wire 3 # str1 [2:0] $end
   $var wire 3 $ str2 [2:0] $end
   $var wire 1 . O $end
   $var wire 32 % i [31:0] $end
   $var wire 32 & j [31:0] $end
   $scope module uut $end
    $var wire 3 # str1 [2:0] $end
    $var wire 3 $ str2 [2:0] $end
    $var wire 1 . O $end
    $var wire 1 / nn1 $end
    $var wire 1 0 xx1 $end
    $var wire 1 1 aa1 $end
    $var wire 1 2 nn2 $end
    $var wire 1 ' xx2 $end
    $var wire 1 3 aa2 $end
    $var wire 1 4 nn3 $end
    $var wire 1 5 aa3 $end
    $var wire 1 6 aa4 $end
    $var wire 1 7 aa5 $end
    $var wire 1 8 oo1 $end
    $var wire 1 9 aa6 $end
    $scope module A1 $end
     $var wire 32 : N [31:0] $end
     $var wire 1 / A [0:0] $end
     $var wire 1 ( B [0:0] $end
     $var wire 1 1 O [0:0] $end
     $var wire 32 ; i [31:0] $end
    $upscope $end
    $scope module A2 $end
     $var wire 32 : N [31:0] $end
     $var wire 1 2 A [0:0] $end
     $var wire 1 ) B [0:0] $end
     $var wire 1 3 O [0:0] $end
     $var wire 32 ; i [31:0] $end
    $upscope $end
    $scope module A3 $end
     $var wire 32 : N [31:0] $end
     $var wire 1 4 A [0:0] $end
     $var wire 1 * B [0:0] $end
     $var wire 1 5 O [0:0] $end
     $var wire 32 ; i [31:0] $end
    $upscope $end
    $scope module A4 $end
     $var wire 32 : N [31:0] $end
     $var wire 1 0 A [0:0] $end
     $var wire 1 3 B [0:0] $end
     $var wire 1 6 O [0:0] $end
     $var wire 32 ; i [31:0] $end
    $upscope $end
    $scope module A5 $end
     $var wire 32 : N [31:0] $end
     $var wire 1 0 A [0:0] $end
     $var wire 1 ' B [0:0] $end
     $var wire 1 7 O [0:0] $end
     $var wire 32 ; i [31:0] $end
    $upscope $end
    $scope module A6 $end
     $var wire 32 : N [31:0] $end
     $var wire 1 7 A [0:0] $end
     $var wire 1 5 B [0:0] $end
     $var wire 1 9 O [0:0] $end
     $var wire 32 ; i [31:0] $end
    $upscope $end
    $scope module N1 $end
     $var wire 32 : N [31:0] $end
     $var wire 1 + A [0:0] $end
     $var wire 1 / O [0:0] $end
     $var wire 32 ; i [31:0] $end
    $upscope $end
    $scope module N2 $end
     $var wire 32 : N [31:0] $end
     $var wire 1 , A [0:0] $end
     $var wire 1 2 O [0:0] $end
     $var wire 32 ; i [31:0] $end
    $upscope $end
    $scope module N3 $end
     $var wire 32 : N [31:0] $end
     $var wire 1 - A [0:0] $end
     $var wire 1 4 O [0:0] $end
     $var wire 32 ; i [31:0] $end
    $upscope $end
    $scope module O1 $end
     $var wire 1 1 A $end
     $var wire 1 6 B $end
     $var wire 1 8 O $end
    $upscope $end
    $scope module O2 $end
     $var wire 1 8 A $end
     $var wire 1 9 B $end
     $var wire 1 . O $end
    $upscope $end
    $scope module X1 $end
     $var wire 1 + A $end
     $var wire 1 ( B $end
     $var wire 1 0 O $end
    $upscope $end
    $scope module X2 $end
     $var wire 1 , A $end
     $var wire 1 ) B $end
     $var wire 1 ' O $end
    $upscope $end
   $upscope $end
  $upscope $end
 $upscope $end
$enddefinitions $end


#0
b000 #
b000 $
b00000000000000000000000000000000 %
b00000000000000000000000000000000 &
1'
0(
0)
0*
0+
0,
0-
0.
1/
10
01
12
03
14
05
06
17
08
09
b00000000000000000000000000000001 :
b00000000000000000000000000000001 ;
#10
b001 $
b00000000000000000000000000000001 &
1*
1.
15
19
#20
b010 $
b00000000000000000000000000000010 &
0'
1)
0*
13
05
16
07
18
09
#30
b011 $
b00000000000000000000000000000011 &
1*
15
#40
b100 $
b00000000000000000000000000000100 &
1'
1(
0)
0*
00
11
03
05
06
#50
b101 $
b00000000000000000000000000000101 &
1*
15
#60
b110 $
b00000000000000000000000000000110 &
0'
1)
0*
13
05
#70
b111 $
b00000000000000000000000000000111 &
1*
15
#80
b001 #
b000 $
b00000000000000000000000000000001 %
b00000000000000000000000000001000 &
1'
0(
0)
0*
1-
0.
10
01
03
04
05
17
08
#90
b001 $
b00000000000000000000000000000001 &
1*
#100
b010 $
b00000000000000000000000000000010 &
0'
1)
0*
1.
13
16
07
18
#110
b011 $
b00000000000000000000000000000011 &
1*
#120
b100 $
b00000000000000000000000000000100 &
1'
1(
0)
0*
00
11
03
06
#130
b101 $
b00000000000000000000000000000101 &
1*
#140
b110 $
b00000000000000000000000000000110 &
0'
1)
0*
13
#150
b111 $
b00000000000000000000000000000111 &
1*
#160
b010 #
b000 $
b00000000000000000000000000000010 %
b00000000000000000000000000001000 &
0(
0)
0*
1,
0-
0.
10
01
02
03
14
08
#170
b001 $
b00000000000000000000000000000001 &
1*
15
#180
b010 $
b00000000000000000000000000000010 &
1'
1)
0*
05
17
#190
b011 $
b00000000000000000000000000000011 &
1*
1.
15
19
#200
b100 $
b00000000000000000000000000000100 &
0'
1(
0)
0*
00
11
05
07
18
09
#210
b101 $
b00000000000000000000000000000101 &
1*
15
#220
b110 $
b00000000000000000000000000000110 &
1'
1)
0*
05
#230
b111 $
b00000000000000000000000000000111 &
1*
15
#240
b011 #
b000 $
b00000000000000000000000000000011 %
b00000000000000000000000000001000 &
0'
0(
0)
0*
1-
0.
10
01
04
05
08
#250
b001 $
b00000000000000000000000000000001 &
1*
#260
b010 $
b00000000000000000000000000000010 &
1'
1)
0*
17
#270
b011 $
b00000000000000000000000000000011 &
1*
#280
b100 $
b00000000000000000000000000000100 &
0'
1(
0)
0*
1.
00
11
07
18
#290
b101 $
b00000000000000000000000000000101 &
1*
#300
b110 $
b00000000000000000000000000000110 &
1'
1)
0*
#310
b111 $
b00000000000000000000000000000111 &
1*
#320
b100 #
b000 $
b00000000000000000000000000000100 %
b00000000000000000000000000001000 &
0(
0)
0*
1+
0,
0-
0.
0/
01
12
14
08
#330
b001 $
b00000000000000000000000000000001 &
1*
15
#340
b010 $
b00000000000000000000000000000010 &
0'
1)
0*
13
05
#350
b011 $
b00000000000000000000000000000011 &
1*
15
#360
b100 $
b00000000000000000000000000000100 &
1'
1(
0)
0*
10
03
05
17
#370
b101 $
b00000000000000000000000000000101 &
1*
1.
15
19
#380
b110 $
b00000000000000000000000000000110 &
0'
1)
0*
13
05
16
07
18
09
#390
b111 $
b00000000000000000000000000000111 &
1*
15
#400
b101 #
b000 $
b00000000000000000000000000000101 %
b00000000000000000000000000001000 &
1'
0(
0)
0*
1-
0.
00
03
04
05
06
08
#410
b001 $
b00000000000000000000000000000001 &
1*
#420
b010 $
b00000000000000000000000000000010 &
0'
1)
0*
13
#430
b011 $
b00000000000000000000000000000011 &
1*
#440
b100 $
b00000000000000000000000000000100 &
1'
1(
0)
0*
10
03
17
#450
b101 $
b00000000000000000000000000000101 &
1*
#460
b110 $
b00000000000000000000000000000110 &
0'
1)
0*
1.
13
16
07
18
#470
b111 $
b00000000000000000000000000000111 &
1*
#480
b110 #
b000 $
b00000000000000000000000000000110 %
b00000000000000000000000000001000 &
0(
0)
0*
1,
0-
0.
00
02
03
14
06
08
#490
b001 $
b00000000000000000000000000000001 &
1*
15
#500
b010 $
b00000000000000000000000000000010 &
1'
1)
0*
05
#510
b011 $
b00000000000000000000000000000011 &
1*
15
#520
b100 $
b00000000000000000000000000000100 &
0'
1(
0)
0*
10
05
#530
b101 $
b00000000000000000000000000000101 &
1*
15
#540
b110 $
b00000000000000000000000000000110 &
1'
1)
0*
05
17
#550
b111 $
b00000000000000000000000000000111 &
1*
1.
15
19
#560
b111 #
b000 $
b00000000000000000000000000000111 %
b00000000000000000000000000001000 &
0'
0(
0)
0*
1-
0.
00
04
05
07
09
#570
b001 $
b00000000000000000000000000000001 &
1*
#580
b010 $
b00000000000000000000000000000010 &
1'
1)
0*
#590
b011 $
b00000000000000000000000000000011 &
1*
#600
b100 $
b00000000000000000000000000000100 &
0'
1(
0)
0*
10
#610
b101 $
b00000000000000000000000000000101 &
1*
#620
b110 $
b00000000000000000000000000000110 &
1'
1)
0*
17
#630
b111 $
b00000000000000000000000000000111 &
1*
#640
b00000000000000000000000000001000 %
b00000000000000000000000000001000 &
