V_primo_elab/Adder1bit.v
module Sommatore #(parameter N = 8)(
	input [N-1:0] A, input [N-1:0] B,
	output [N-1:0] O);
	
	assign O = A + B;
	
endmodule

V_primo_elab/reg_parallelo.v
module registroparallelo #( parameter N = 8)(
	input [N-1:0] D,
	input clock,
	output [N-1:0] Q
	);
	reg [N-1:0] dato = {N{1'b0}};
	assign Q = dato;
	always @(posedge clock)
		begin dato = D;
	end
endmodule

V_primo_elab/counter_12.v
module contatore(
	input CLK,
	output reg [3:0] O = 4'd0
	);
	
	parameter N = 4;
	
	reg [3:0] costante = 4'd1;
	wire [3:0] w, w2;
	
	
	registroparallelo #(N) parall(
		.D(w),
		.clock(CLK),
		.Q(w2)
	);
	
	Sommatore #(N) Sum (
		.A(costante),
		.B(w2),
		.O(w)
	);
	
	always @(posedge CLK) begin
		if(w2 < 4'd12) begin
			O <= w2;
		end else begin
			O <= 4'd0;
		end
	end
	
	
	
endmodule

V_primo_elab/tb_contatore.v
module contatore_tb();


	reg Clock;
	wire [3:0] out;
	
	
	contatore count (
		.CLK(Clock),
		.O(out)
	);
	
	
	always #5 Clock = ~Clock;
	
	
	initial begin
		
		$dumpfile("contatore.vcd");
		$dumpvars(0, contatore_tb);
		$monitor("time=%0t  CLK=%b  O=%b", $time, Clock, out);
	
		Clock = 1'b0;
		#150	
		
		$finish;
	end
	

endmodule

V_primo_elab/contatore.vcd
$version Generated by VerilatedVcd $end
$timescale 1ps $end
 $scope module TOP $end
  $scope module contatore_tb $end
   $var wire 1 # Clock $end
   $var wire 4 $ out [3:0] $end
   $scope module count $end
    $var wire 1 # CLK $end
    $var wire 4 $ O [3:0] $end
    $var wire 32 ' N [31:0] $end
    $var wire 4 ( costante [3:0] $end
    $var wire 4 % w [3:0] $end
    $var wire 4 & w2 [3:0] $end
    $scope module Sum $end
     $var wire 32 ' N [31:0] $end
     $var wire 4 ( A [3:0] $end
     $var wire 4 & B [3:0] $end
     $var wire 4 % O [3:0] $end
    $upscope $end
    $scope module parall $end
     $var wire 32 ' N [31:0] $end
     $var wire 4 % D [3:0] $end
     $var wire 1 # clock $end
     $var wire 4 & Q [3:0] $end
     $var wire 4 & dato [3:0] $end
    $upscope $end
   $upscope $end
  $upscope $end
 $upscope $end
$enddefinitions $end


#0
0#
b0000 $
b0001 %
b0000 &
b00000000000000000000000000000100 '
b0001 (
#5
1#
#10
0#
b0010 %
b0001 &
#15
1#
b0001 $
#20
0#
b0011 %
b0010 &
#25
1#
b0010 $
#30
0#
b0100 %
b0011 &
#35
1#
b0011 $
#40
0#
b0101 %
b0100 &
#45
1#
b0100 $
#50
0#
b0110 %
b0101 &
#55
1#
b0101 $
#60
0#
b0111 %
b0110 &
#65
1#
b0110 $
#70
0#
b1000 %
b0111 &
#75
1#
b0111 $
#80
0#
b1001 %
b1000 &
#85
1#
b1000 $
#90
0#
b1010 %
b1001 &
#95
1#
b1001 $
#100
0#
b1011 %
b1010 &
#105
1#
b1010 $
#110
0#
b1100 %
b1011 &
#115
1#
b1011 $
#120
0#
b1101 %
b1100 &
#125
1#
b0000 $
#130
0#
b1110 %
b1101 &
#135
1#
#140
0#
b1111 %
b1110 &
#145
1#
#150
0#
b0000 %
b1111 &
