V_primo_elab/Regparallelofe.v
module registroparallelofe #( parameter N = 8)(
	input [N-1:0] D,
	input clock,
	output [N-1:0] Q
	);
	reg [N-1:0] dato = {N{1'b0}};
	assign Q = dato;
	always @(negedge clock) begin
		dato = D;
	end
endmodule

V_primo_elab/tb_fereg.v
module tb_regfe();

	parameter p = 4;
	integer i;

	reg [p-1:0] A;
	reg C;
	wire [p-1:0] out;
	
	
	
	registroparallelofe #(p) dut(
		.D(A),
		.clock(C),
		.Q(out)	
	);
	
	
	
	initial begin
	
		$dumpfile("Simregfe.vcd");
		$dumpvars(0, tb_regfe);
	
		A = 4'b1010;
	
      		for (i = 0; i < 10; i = i + 1) begin
        		#5 C = ~C;  // fronte di salita
        		#5 C = ~C;  // fronte di discesa
        	end
        	
        	
        	$finish;
        	
        end
        
        
        
endmodule

V_primo_elab/Simregfe.vcd
$version Generated by VerilatedVcd $end
$timescale 1ps $end
 $scope module TOP $end
  $scope module tb_regfe $end
   $var wire 32 ' p [31:0] $end
   $var wire 32 # i [31:0] $end
   $var wire 4 $ A [3:0] $end
   $var wire 1 % C $end
   $var wire 4 & out [3:0] $end
   $scope module dut $end
    $var wire 32 ' N [31:0] $end
    $var wire 4 $ D [3:0] $end
    $var wire 1 % clock $end
    $var wire 4 & Q [3:0] $end
    $var wire 4 & dato [3:0] $end
   $upscope $end
  $upscope $end
 $upscope $end
$enddefinitions $end


#0
b00000000000000000000000000000000 #
b1010 $
0%
b0000 &
b00000000000000000000000000000100 '
#5
1%
#10
b00000000000000000000000000000001 #
0%
b1010 &
#15
1%
#20
b00000000000000000000000000000010 #
0%
#25
1%
#30
b00000000000000000000000000000011 #
0%
#35
1%
#40
b00000000000000000000000000000100 #
0%
#45
1%
#50
b00000000000000000000000000000101 #
0%
#55
1%
#60
b00000000000000000000000000000110 #
0%
#65
1%
#70
b00000000000000000000000000000111 #
0%
#75
1%
#80
b00000000000000000000000000001000 #
0%
#85
1%
#90
b00000000000000000000000000001001 #
0%
#95
1%
#100
b00000000000000000000000000001010 #
0%
