V_primo_elab/reg_parallelo.v
module registroparallelo #( parameter N = 8)(
	input [N-1:0] D,
	input clock,
	output [N-1:0] Q
	);
	reg [N-1:0] dato = {N{1'b0}};
	assign Q = dato;
	always @(posedge clock)
		begin dato = D;
	end
endmodule

V_primo_elab/Mux2entrate.v
module mux2 #(parameter N = 4)(
	input [N-1:0] A, B,
	input seg_ctrl,
	output reg [N-1:0] O
);

	always @(A, B, seg_ctrl) begin
		case(seg_ctrl)
		1'b0: O = A;
		1'b1: O = B;
		endcase
	end
	
endmodule

V_primo_elab/Mux2ingreg.v
module mux_reg_2ing #(parameter N = 3)(
	input [N-1:0] a1,
	input [N-1:0] a0,
	input cntrl,
	input Clock,
	output [N-1:0] out
	);

	wire [N-1:0] muxreg;

	mux2 #(N) m1(
		.seg_ctrl(cntrl),
		.A(a1),
		.B(a0),
		.O(muxreg)
	);



	registroparallelo #(N) regpar(
		.D(muxreg),
		.clock(Clock),
		.Q(out)
	);
	
	
endmodule

V_primo_elab/mux3entrate.v
module multiplexer #(parameter N = 8) (
	input [1:0] S, input [N-1:0] A3, input [N-1:0] A2,
	input [N-1:0] A1,
	output reg [N-1:0] O);
	always @(A3, A2, A1, S) begin
		case(S)
		2'b01: O = A1;
		2'b10: O = A2;
		2'b11: O = A3;
		default: O = {N{1'b0}};
		endcase
	end
endmodule

V_primo_elab/mux3ingreg.v
module mux_reg #(parameter N = 3)(
	input [N-1:0] a3,
	input [N-1:0] a2,
	input [N-1:0] a1,
	input [1:0] control,
	input Clock,
	output [N-1:0] out
	);

	wire [N-1:0] muxreg;

	multiplexer #(N) m1(
		.S(control),
		.A3(a3),
		.A2(a2),
		.A1(a1),
		.O(muxreg)
	);



	registroparallelo #(N) regpar(
		.D(muxreg),
		.clock(Clock),
		.Q(out)
	);
	
	
endmodule

V_primo_elab/S1.v
module Stato1(

	input [5:0] A1, A2, A3,
	input [1:0] Ctrl,
	input [9:0] B1, B2, B3,
	input [5:0] C1, C2, C3,
	
	input Ctrl_mux9, Ctrl_mux5,
	
	input [5:0] D0, D1, E0, E1, F0, F1, G0, G1, H0, H1, I0, I1, J0, J1, K0, K1,
	
	input clock,

	output [5:0] OA, OC, OD, OE, OF, OG, OH, OI, OJ, OK,
	output [9:0] OB

);



	mux_reg #(6) m1(
		.a1(A1),
		.a2(A2),
		.a3(A3),
		.control(Ctrl),
		.Clock(clock),
		.out(OA)
	);
	
	
	mux_reg #(10) m2(
		.a1(B1),
		.a2(B2),
		.a3(B3),
		.control(Ctrl),
		.Clock(clock),
		.out(OB)
	);	
	
	
	mux_reg #(6) m3(
		.a1(C1),
		.a2(C2),
		.a3(C3),
		.control(Ctrl),
		.Clock(clock),
		.out(OC)
	);
	
	
	
	
	
	mux_reg_2ing #(6) m5(
		.a1(H0),
		.a0(H1),
		.cntrl(Ctrl_mux5),
		.Clock(clock),
		.out(OH)
	);
	
	
	mux_reg_2ing #(6) m6(
		.a1(I0),
		.a0(I1),
		.cntrl(Ctrl_mux5),
		.Clock(clock),
		.out(OI)
	);
	

	mux_reg_2ing #(6) m7(
		.a1(J0),
		.a0(J1),
		.cntrl(Ctrl_mux5),
		.Clock(clock),
		.out(OJ)
	);
	
	
	mux_reg_2ing #(6) m8(
		.a1(K0),
		.a0(K1),
		.cntrl(Ctrl_mux5),
		.Clock(clock),
		.out(OK)
	);
		
	
	
	
	
	mux_reg_2ing #(6) m9(
		.a1(D0),
		.a0(D1),
		.cntrl(Ctrl_mux9),
		.Clock(clock),
		.out(OD)
	);
	
	
	mux_reg_2ing #(6) m10(
		.a1(E0),
		.a0(E1),
		.cntrl(Ctrl_mux9),
		.Clock(clock),
		.out(OE)
	);
	

	mux_reg_2ing #(6) m11(
		.a1(F0),
		.a0(F1),
		.cntrl(Ctrl_mux9),
		.Clock(clock),
		.out(OF)
	);
	
	
	mux_reg_2ing #(6) m12(
		.a1(G0),
		.a0(G1),
		.cntrl(Ctrl_mux9),
		.Clock(clock),
		.out(OG)
	);
	
	
endmodule

//verilator --trace --binary tb_S1.v S1.v Mux2ingreg.v mux3ingreg.v reg_parallelo.v Mux2entrate.v mux3entrate.v --top-module tb_Stato1 -o provaS1

V_primo_elab/tb_S1.v
`timescale 1ns/1ps

module tb_Stato1;

	integer i;

    // ingressi
    reg [5:0] A1, A2, A3;
    reg [9:0] B1, B2, B3;
    reg [5:0] C1, C2, C3;

    reg [5:0] D0, D1, E0, E1, F0, F1, G0, G1, H0, H1, I0, I1, J0, J1, K0, K1;

    reg [1:0] Ctrl;
    reg Ctrl_mux9, Ctrl_mux5;
    reg clock;

    // uscite
    wire [5:0] OA, OC, OD, OE, OF, OG, OH, OI, OJ, OK;
    wire [9:0] OB;

    // istanza del DUT (Device Under Test)
    Stato1 dut (

        .A1(A1), .A2(A2), .A3(A3),
        .B1(B1), .B2(B2), .B3(B3),
        .C1(C1), .C2(C2), .C3(C3),

        .Ctrl(Ctrl),
        .Ctrl_mux9(Ctrl_mux9),
        .Ctrl_mux5(Ctrl_mux5),

        .D0(D0), .D1(D1),
        .E0(E0), .E1(E1),
        .F0(F0), .F1(F1),
        .G0(G0), .G1(G1),
        .H0(H0), .H1(H1),
        .I0(I0), .I1(I1),
        .J0(J0), .J1(J1),
        .K0(K0), .K1(K1),

        .clock(clock),

        .OA(OA),
        .OB(OB),
        .OC(OC),
        .OD(OD),
        .OE(OE),
        .OF(OF),
        .OG(OG),
        .OH(OH),
        .OI(OI),
        .OJ(OJ),
        .OK(OK)
    );


	initial begin
		clock = 0;
	end


	always #5 clock = ~clock;


	initial begin

		$dumpfile("SimS1.vcd");
		$dumpvars(0, tb_Stato1);
       	

        	// inizializzazione ingressi
       		A1 = 6'd1;  A2 = 6'd2;  A3 = 6'd3;
        	B1 = 10'd10; B2 = 10'd20; B3 = 10'd30;
        	C1 = 6'd4;  C2 = 6'd5;  C3 = 6'd6;

        	D0 = 6'd7;  D1 = 6'd8;
        	E0 = 6'd9;  E1 = 6'd10;
        	F0 = 6'd11; F1 = 6'd12;
        	G0 = 6'd13; G1 = 6'd14;
        	H0 = 6'd10; H1 = 6'd7;
        	I0 = 6'd7; I1 = 6'd13;
        	J0 = 6'd17; J1 = 6'd20;
        	K0 = 6'd30; K1 = 6'd35;

        	Ctrl = 2'b00;
        	Ctrl_mux9 = 0;
		Ctrl_mux5 = 0;

        	#20;

       		// test selezioni mux a 3 ingressi
        	Ctrl = 2'b01;
        	#20;

        	Ctrl = 2'b10;
        	#20;

        	// test mux a 2 ingressi
        	Ctrl_mux9 = 1;
        	#20;

        	Ctrl_mux9 = 0;
        	#20;

        	// cambio valori per nuovo test
        	A1 = 6'd15; A2 = 6'd16; A3 = 6'd17;
        	B1 = 10'd100; B2 = 10'd200; B3 = 10'd300;
        	C1 = 6'd18; C2 = 6'd19; C3 = 6'd20;

        	Ctrl = 2'b00;
        	Ctrl_mux9 = 1;

        	#40;

        	$finish;

    	end
    	
    	
    	

endmodule

V_primo_elab/SimS1.vcd
$version Generated by VerilatedVcd $end
$timescale 1ps $end
 $scope module TOP $end
  $scope module tb_Stato1 $end
   $var wire 32 V i [31:0] $end
   $var wire 6 # A1 [5:0] $end
   $var wire 6 $ A2 [5:0] $end
   $var wire 6 % A3 [5:0] $end
   $var wire 10 & B1 [9:0] $end
   $var wire 10 ' B2 [9:0] $end
   $var wire 10 ( B3 [9:0] $end
   $var wire 6 ) C1 [5:0] $end
   $var wire 6 * C2 [5:0] $end
   $var wire 6 + C3 [5:0] $end
   $var wire 6 , D0 [5:0] $end
   $var wire 6 - D1 [5:0] $end
   $var wire 6 . E0 [5:0] $end
   $var wire 6 / E1 [5:0] $end
   $var wire 6 0 F0 [5:0] $end
   $var wire 6 1 F1 [5:0] $end
   $var wire 6 2 G0 [5:0] $end
   $var wire 6 3 G1 [5:0] $end
   $var wire 6 4 H0 [5:0] $end
   $var wire 6 5 H1 [5:0] $end
   $var wire 6 6 I0 [5:0] $end
   $var wire 6 7 I1 [5:0] $end
   $var wire 6 8 J0 [5:0] $end
   $var wire 6 9 J1 [5:0] $end
   $var wire 6 : K0 [5:0] $end
   $var wire 6 ; K1 [5:0] $end
   $var wire 2 < Ctrl [1:0] $end
   $var wire 1 = Ctrl_mux9 $end
   $var wire 1 > Ctrl_mux5 $end
   $var wire 1 U clock $end
   $var wire 6 J OA [5:0] $end
   $var wire 6 K OC [5:0] $end
   $var wire 6 L OD [5:0] $end
   $var wire 6 M OE [5:0] $end
   $var wire 6 N OF [5:0] $end
   $var wire 6 O OG [5:0] $end
   $var wire 6 P OH [5:0] $end
   $var wire 6 Q OI [5:0] $end
   $var wire 6 R OJ [5:0] $end
   $var wire 6 S OK [5:0] $end
   $var wire 10 T OB [9:0] $end
   $scope module dut $end
    $var wire 6 # A1 [5:0] $end
    $var wire 6 $ A2 [5:0] $end
    $var wire 6 % A3 [5:0] $end
    $var wire 2 < Ctrl [1:0] $end
    $var wire 10 & B1 [9:0] $end
    $var wire 10 ' B2 [9:0] $end
    $var wire 10 ( B3 [9:0] $end
    $var wire 6 ) C1 [5:0] $end
    $var wire 6 * C2 [5:0] $end
    $var wire 6 + C3 [5:0] $end
    $var wire 1 = Ctrl_mux9 $end
    $var wire 1 > Ctrl_mux5 $end
    $var wire 6 , D0 [5:0] $end
    $var wire 6 - D1 [5:0] $end
    $var wire 6 . E0 [5:0] $end
    $var wire 6 / E1 [5:0] $end
    $var wire 6 0 F0 [5:0] $end
    $var wire 6 1 F1 [5:0] $end
    $var wire 6 2 G0 [5:0] $end
    $var wire 6 3 G1 [5:0] $end
    $var wire 6 4 H0 [5:0] $end
    $var wire 6 5 H1 [5:0] $end
    $var wire 6 6 I0 [5:0] $end
    $var wire 6 7 I1 [5:0] $end
    $var wire 6 8 J0 [5:0] $end
    $var wire 6 9 J1 [5:0] $end
    $var wire 6 : K0 [5:0] $end
    $var wire 6 ; K1 [5:0] $end
    $var wire 1 U clock $end
    $var wire 6 J OA [5:0] $end
    $var wire 6 K OC [5:0] $end
    $var wire 6 L OD [5:0] $end
    $var wire 6 M OE [5:0] $end
    $var wire 6 N OF [5:0] $end
    $var wire 6 O OG [5:0] $end
    $var wire 6 P OH [5:0] $end
    $var wire 6 Q OI [5:0] $end
    $var wire 6 R OJ [5:0] $end
    $var wire 6 S OK [5:0] $end
    $var wire 10 T OB [9:0] $end
    $scope module m1 $end
     $var wire 32 W N [31:0] $end
     $var wire 6 % a3 [5:0] $end
     $var wire 6 $ a2 [5:0] $end
     $var wire 6 # a1 [5:0] $end
     $var wire 2 < control [1:0] $end
     $var wire 1 U Clock $end
     $var wire 6 J out [5:0] $end
     $var wire 6 ? muxreg [5:0] $end
     $scope module m1 $end
      $var wire 32 W N [31:0] $end
      $var wire 2 < S [1:0] $end
      $var wire 6 % A3 [5:0] $end
      $var wire 6 $ A2 [5:0] $end
      $var wire 6 # A1 [5:0] $end
      $var wire 6 ? O [5:0] $end
     $upscope $end
     $scope module regpar $end
      $var wire 32 W N [31:0] $end
      $var wire 6 ? D [5:0] $end
      $var wire 1 U clock $end
      $var wire 6 J Q [5:0] $end
      $var wire 6 J dato [5:0] $end
     $upscope $end
    $upscope $end
    $scope module m10 $end
     $var wire 32 W N [31:0] $end
     $var wire 6 . a1 [5:0] $end
     $var wire 6 / a0 [5:0] $end
     $var wire 1 = cntrl $end
     $var wire 1 U Clock $end
     $var wire 6 M out [5:0] $end
     $var wire 6 @ muxreg [5:0] $end
     $scope module m1 $end
      $var wire 32 W N [31:0] $end
      $var wire 6 . A [5:0] $end
      $var wire 6 / B [5:0] $end
      $var wire 1 = seg_ctrl $end
      $var wire 6 @ O [5:0] $end
     $upscope $end
     $scope module regpar $end
      $var wire 32 W N [31:0] $end
      $var wire 6 @ D [5:0] $end
      $var wire 1 U clock $end
      $var wire 6 M Q [5:0] $end
      $var wire 6 M dato [5:0] $end
     $upscope $end
    $upscope $end
    $scope module m11 $end
     $var wire 32 W N [31:0] $end
     $var wire 6 0 a1 [5:0] $end
     $var wire 6 1 a0 [5:0] $end
     $var wire 1 = cntrl $end
     $var wire 1 U Clock $end
     $var wire 6 N out [5:0] $end
     $var wire 6 A muxreg [5:0] $end
     $scope module m1 $end
      $var wire 32 W N [31:0] $end
      $var wire 6 0 A [5:0] $end
      $var wire 6 1 B [5:0] $end
      $var wire 1 = seg_ctrl $end
      $var wire 6 A O [5:0] $end
     $upscope $end
     $scope module regpar $end
      $var wire 32 W N [31:0] $end
      $var wire 6 A D [5:0] $end
      $var wire 1 U clock $end
      $var wire 6 N Q [5:0] $end
      $var wire 6 N dato [5:0] $end
     $upscope $end
    $upscope $end
    $scope module m12 $end
     $var wire 32 W N [31:0] $end
     $var wire 6 2 a1 [5:0] $end
     $var wire 6 3 a0 [5:0] $end
     $var wire 1 = cntrl $end
     $var wire 1 U Clock $end
     $var wire 6 O out [5:0] $end
     $var wire 6 B muxreg [5:0] $end
     $scope module m1 $end
      $var wire 32 W N [31:0] $end
      $var wire 6 2 A [5:0] $end
      $var wire 6 3 B [5:0] $end
      $var wire 1 = seg_ctrl $end
      $var wire 6 B O [5:0] $end
     $upscope $end
     $scope module regpar $end
      $var wire 32 W N [31:0] $end
      $var wire 6 B D [5:0] $end
      $var wire 1 U clock $end
      $var wire 6 O Q [5:0] $end
      $var wire 6 O dato [5:0] $end
     $upscope $end
    $upscope $end
    $scope module m2 $end
     $var wire 32 X N [31:0] $end
     $var wire 10 ( a3 [9:0] $end
     $var wire 10 ' a2 [9:0] $end
     $var wire 10 & a1 [9:0] $end
     $var wire 2 < control [1:0] $end
     $var wire 1 U Clock $end
     $var wire 10 T out [9:0] $end
     $var wire 10 C muxreg [9:0] $end
     $scope module m1 $end
      $var wire 32 X N [31:0] $end
      $var wire 2 < S [1:0] $end
      $var wire 10 ( A3 [9:0] $end
      $var wire 10 ' A2 [9:0] $end
      $var wire 10 & A1 [9:0] $end
      $var wire 10 C O [9:0] $end
     $upscope $end
     $scope module regpar $end
      $var wire 32 X N [31:0] $end
      $var wire 10 C D [9:0] $end
      $var wire 1 U clock $end
      $var wire 10 T Q [9:0] $end
      $var wire 10 T dato [9:0] $end
     $upscope $end
    $upscope $end
    $scope module m3 $end
     $var wire 32 W N [31:0] $end
     $var wire 6 + a3 [5:0] $end
     $var wire 6 * a2 [5:0] $end
     $var wire 6 ) a1 [5:0] $end
     $var wire 2 < control [1:0] $end
     $var wire 1 U Clock $end
     $var wire 6 K out [5:0] $end
     $var wire 6 D muxreg [5:0] $end
     $scope module m1 $end
      $var wire 32 W N [31:0] $end
      $var wire 2 < S [1:0] $end
      $var wire 6 + A3 [5:0] $end
      $var wire 6 * A2 [5:0] $end
      $var wire 6 ) A1 [5:0] $end
      $var wire 6 D O [5:0] $end
     $upscope $end
     $scope module regpar $end
      $var wire 32 W N [31:0] $end
      $var wire 6 D D [5:0] $end
      $var wire 1 U clock $end
      $var wire 6 K Q [5:0] $end
      $var wire 6 K dato [5:0] $end
     $upscope $end
    $upscope $end
    $scope module m5 $end
     $var wire 32 W N [31:0] $end
     $var wire 6 4 a1 [5:0] $end
     $var wire 6 5 a0 [5:0] $end
     $var wire 1 > cntrl $end
     $var wire 1 U Clock $end
     $var wire 6 P out [5:0] $end
     $var wire 6 E muxreg [5:0] $end
     $scope module m1 $end
      $var wire 32 W N [31:0] $end
      $var wire 6 4 A [5:0] $end
      $var wire 6 5 B [5:0] $end
      $var wire 1 > seg_ctrl $end
      $var wire 6 E O [5:0] $end
     $upscope $end
     $scope module regpar $end
      $var wire 32 W N [31:0] $end
      $var wire 6 E D [5:0] $end
      $var wire 1 U clock $end
      $var wire 6 P Q [5:0] $end
      $var wire 6 P dato [5:0] $end
     $upscope $end
    $upscope $end
    $scope module m6 $end
     $var wire 32 W N [31:0] $end
     $var wire 6 6 a1 [5:0] $end
     $var wire 6 7 a0 [5:0] $end
     $var wire 1 > cntrl $end
     $var wire 1 U Clock $end
     $var wire 6 Q out [5:0] $end
     $var wire 6 F muxreg [5:0] $end
     $scope module m1 $end
      $var wire 32 W N [31:0] $end
      $var wire 6 6 A [5:0] $end
      $var wire 6 7 B [5:0] $end
      $var wire 1 > seg_ctrl $end
      $var wire 6 F O [5:0] $end
     $upscope $end
     $scope module regpar $end
      $var wire 32 W N [31:0] $end
      $var wire 6 F D [5:0] $end
      $var wire 1 U clock $end
      $var wire 6 Q Q [5:0] $end
      $var wire 6 Q dato [5:0] $end
     $upscope $end
    $upscope $end
    $scope module m7 $end
     $var wire 32 W N [31:0] $end
     $var wire 6 8 a1 [5:0] $end
     $var wire 6 9 a0 [5:0] $end
     $var wire 1 > cntrl $end
     $var wire 1 U Clock $end
     $var wire 6 R out [5:0] $end
     $var wire 6 G muxreg [5:0] $end
     $scope module m1 $end
      $var wire 32 W N [31:0] $end
      $var wire 6 8 A [5:0] $end
      $var wire 6 9 B [5:0] $end
      $var wire 1 > seg_ctrl $end
      $var wire 6 G O [5:0] $end
     $upscope $end
     $scope module regpar $end
      $var wire 32 W N [31:0] $end
      $var wire 6 G D [5:0] $end
      $var wire 1 U clock $end
      $var wire 6 R Q [5:0] $end
      $var wire 6 R dato [5:0] $end
     $upscope $end
    $upscope $end
    $scope module m8 $end
     $var wire 32 W N [31:0] $end
     $var wire 6 : a1 [5:0] $end
     $var wire 6 ; a0 [5:0] $end
     $var wire 1 > cntrl $end
     $var wire 1 U Clock $end
     $var wire 6 S out [5:0] $end
     $var wire 6 H muxreg [5:0] $end
     $scope module m1 $end
      $var wire 32 W N [31:0] $end
      $var wire 6 : A [5:0] $end
      $var wire 6 ; B [5:0] $end
      $var wire 1 > seg_ctrl $end
      $var wire 6 H O [5:0] $end
     $upscope $end
     $scope module regpar $end
      $var wire 32 W N [31:0] $end
      $var wire 6 H D [5:0] $end
      $var wire 1 U clock $end
      $var wire 6 S Q [5:0] $end
      $var wire 6 S dato [5:0] $end
     $upscope $end
    $upscope $end
    $scope module m9 $end
     $var wire 32 W N [31:0] $end
     $var wire 6 , a1 [5:0] $end
     $var wire 6 - a0 [5:0] $end
     $var wire 1 = cntrl $end
     $var wire 1 U Clock $end
     $var wire 6 L out [5:0] $end
     $var wire 6 I muxreg [5:0] $end
     $scope module m1 $end
      $var wire 32 W N [31:0] $end
      $var wire 6 , A [5:0] $end
      $var wire 6 - B [5:0] $end
      $var wire 1 = seg_ctrl $end
      $var wire 6 I O [5:0] $end
     $upscope $end
     $scope module regpar $end
      $var wire 32 W N [31:0] $end
      $var wire 6 I D [5:0] $end
      $var wire 1 U clock $end
      $var wire 6 L Q [5:0] $end
      $var wire 6 L dato [5:0] $end
     $upscope $end
    $upscope $end
   $upscope $end
  $upscope $end
 $upscope $end
$enddefinitions $end


#0
b000001 #
b000010 $
b000011 %
b0000001010 &
b0000010100 '
b0000011110 (
b000100 )
b000101 *
b000110 +
b000111 ,
b001000 -
b001001 .
b001010 /
b001011 0
b001100 1
b001101 2
b001110 3
b001010 4
b000111 5
b000111 6
b001101 7
b010001 8
b010100 9
b011110 :
b100011 ;
b00 <
0=
0>
b000000 ?
b001001 @
b001011 A
b001101 B
b0000000000 C
b000000 D
b001010 E
b000111 F
b010001 G
b011110 H
b000111 I
b000000 J
b000000 K
b000000 L
b000000 M
b000000 N
b000000 O
b000000 P
b000000 Q
b000000 R
b000000 S
b0000000000 T
0U
b00000000000000000000000000000000 V
b00000000000000000000000000000110 W
b00000000000000000000000000001010 X
#5000
b000111 L
b001001 M
b001011 N
b001101 O
b001010 P
b000111 Q
b010001 R
b011110 S
1U
#10000
0U
#15000
1U
#20000
b01 <
b000001 ?
b0000001010 C
b000100 D
0U
#25000
b000001 J
b000100 K
b0000001010 T
1U
#30000
0U
#35000
1U
#40000
b10 <
b000010 ?
b0000010100 C
b000101 D
0U
#45000
b000010 J
b000101 K
b0000010100 T
1U
#50000
0U
#55000
1U
#60000
1=
b001010 @
b001100 A
b001110 B
b001000 I
0U
#65000
b001000 L
b001010 M
b001100 N
b001110 O
1U
#70000
0U
#75000
1U
#80000
0=
b001001 @
b001011 A
b001101 B
b000111 I
0U
#85000
b000111 L
b001001 M
b001011 N
b001101 O
1U
#90000
0U
#95000
1U
#100000
b001111 #
b010000 $
b010001 %
b0001100100 &
b0011001000 '
b0100101100 (
b010010 )
b010011 *
b010100 +
b00 <
1=
b000000 ?
b001010 @
b001100 A
b001110 B
b0000000000 C
b000000 D
b001000 I
0U
#105000
b000000 J
b000000 K
b001000 L
b001010 M
b001100 N
b001110 O
b0000000000 T
1U
