V_primo_elab/Regparallenable.v
module registrope_en #( parameter N = 8)(
	input [N-1:0] D,
	input clock, enable,
	output [N-1:0] Q
	);
	reg [N-1:0] dato = {N{1'b0}};
	assign Q = dato;
	always @(posedge clock) begin
		if(enable == 1) begin
			dato = D;
		end
	end
endmodule

V_primo_elab/Decoder.v
module Decoder #(parameter N = 8)(
	input [N-1:0] A, output reg [(2**N)-1:0] O
	);
	integer i;
	always @(A) begin
		for(i = 0; i < (2**N); i = i + 1) begin
			if(i[N-1:0] == A) O[i] = 1'b1;
			else O[i] = 1'b0;
		end
	end
endmodule

V_primo_elab/Demux_ctrl4.v
module demux(
	input [3:0] ctrl,
	input [2:0] in,
	output reg [2:0] out0,
	output reg [2:0] out1,
	output reg [2:0] out2,
	output reg [2:0] out3,
	output reg [2:0] out4,
	output reg [2:0] out5,
	output reg [2:0] out6,
	output reg [2:0] out7,
	output reg [2:0] out8,
	output reg [2:0] out9,
	output reg [2:0] out10,
	output reg [2:0] out11
	);
	
	
	
	
	
	always @(ctrl, in) begin
	
		case(ctrl)
			4'b0000: begin
				out0 = in;
				out1 = 3'b000;
				out2 = 3'b000;
				out3 = 3'b000;
				out4 = 3'b000;
				out5 = 3'b000;
				out6 = 3'b000;
				out7 = 3'b000;
				out8 = 3'b000;	
				out9 = 3'b000;
				out10 = 3'b000;
				out11 = 3'b000;
			end
			4'b0001: begin
				out0 = 3'b000;
				out1 = in;
				out2 = 3'b000;
				out3 = 3'b000;
				out4 = 3'b000;
				out5 = 3'b000;
				out6 = 3'b000;
				out7 = 3'b000;
				out8 = 3'b000;	
				out9 = 3'b000;
				out10 = 3'b000;
				out11 = 3'b000;
			end			
			4'b0010: begin
				out0 = 3'b000;
				out1 = 3'b000;
				out2 = in;
				out3 = 3'b000;
				out4 = 3'b000;
				out5 = 3'b000;
				out6 = 3'b000;
				out7 = 3'b000;
				out8 = 3'b000;	
				out9 = 3'b000;
				out10 = 3'b000;
				out11 = 3'b000;
			end
			4'b0011: begin
				out0 = 3'b000;
				out1 = 3'b000;
				out2 = 3'b000;
				out3 = in;
				out4 = 3'b000;
				out5 = 3'b000;
				out6 = 3'b000;
				out7 = 3'b000;
				out8 = 3'b000;	
				out9 = 3'b000;
				out10 = 3'b000;
				out11 = 3'b000;
			end					
			4'b0100: begin
				out0 = 3'b000;
				out1 = 3'b000;
				out2 = 3'b000;
				out3 = 3'b000;
				out4 = in;
				out5 = 3'b000;
				out6 = 3'b000;
				out7 = 3'b000;
				out8 = 3'b000;	
				out9 = 3'b000;
				out10 = 3'b000;
				out11 = 3'b000;
			end
			4'b0101: begin
				out0 = 3'b000;
				out1 = 3'b000;
				out2 = 3'b000;
				out3 = 3'b000;
				out4 = 3'b000;
				out5 = in;
				out6 = 3'b000;
				out7 = 3'b000;
				out8 = 3'b000;	
				out9 = 3'b000;
				out10 = 3'b000;
				out11 = 3'b000;
			end			
			4'b0110: begin
				out0 = 3'b000;
				out1 = 3'b000;
				out2 = 3'b000;
				out3 = 3'b000;
				out4 = 3'b000;
				out5 = 3'b000;
				out6 = in;
				out7 = 3'b000;
				out8 = 3'b000;	
				out9 = 3'b000;
				out10 = 3'b000;
				out11 = 3'b000;
			end
			4'b0111: begin
				out0 = 3'b000;
				out1 = 3'b000;
				out2 = 3'b000;
				out3 = 3'b000;
				out4 = 3'b000;
				out5 = 3'b000;
				out6 = 3'b000;
				out7 = in;
				out8 = 3'b000;	
				out9 = 3'b000;
				out10 = 3'b000;
				out11 = 3'b000;
			end		
			4'b1000: begin
				out0 = 3'b000;
				out1 = 3'b000;
				out2 = 3'b000;
				out3 = 3'b000;
				out4 = 3'b000;
				out5 = 3'b000;
				out6 = 3'b000;
				out7 = 3'b000;
				out8 = in;	
				out9 = 3'b000;
				out10 = 3'b000;
				out11 = 3'b000;
			end
			4'b1001: begin
				out0 = 3'b000;
				out1 = 3'b000;
				out2 = 3'b000;
				out3 = 3'b000;
				out4 = 3'b000;
				out5 = 3'b000;
				out6 = 3'b000;
				out7 = 3'b000;
				out8 = 3'b000;	
				out9 = in;
				out10 = 3'b000;
				out11 = 3'b000;
			end			
			4'b1010: begin
				out0 = 3'b000;
				out1 = 3'b000;
				out2 = 3'b000;
				out3 = 3'b000;
				out4 = 3'b000;
				out5 = 3'b000;
				out6 = 3'b000;
				out7 = 3'b000;
				out8 = 3'b000;	
				out9 = 3'b000;
				out10 = in;
				out11 = 3'b000;
			end
			4'b1011: begin
				out0 = 3'b000;
				out1 = 3'b000;
				out2 = 3'b000;
				out3 = 3'b000;
				out4 = 3'b000;
				out5 = 3'b000;
				out6 = 3'b000;
				out7 = 3'b000;
				out8 = 3'b000;	
				out9 = 3'b000;
				out10 = 3'b000;
				out11 = in;
			end	
			default: begin
				out0 = 3'b000;
				out1 = 3'b000;
				out2 = 3'b000;
				out3 = 3'b000;
				out4 = 3'b000;
				out5 = 3'b000;
				out6 = 3'b000;
				out7 = 3'b000;
				out8 = 3'b000;	
				out9 = 3'b000;
				out10 = 3'b000;
				out11 = 3'b000;								
			end
		endcase
		
	end
				
endmodule

V_primo_elab/Adder1bit.v
module Sommatore #(parameter N = 8)(
	input [N-1:0] A, input [N-1:0] B,
	output [N-1:0] O);
	
	assign O = A + B;
	
endmodule

V_primo_elab/reg_parallelo.v
module registroparallelo #( parameter N = 8)(
	input [N-1:0] D,
	input clock,
	output [N-1:0] Q
	);
	reg [N-1:0] dato = {N{1'b0}};
	assign Q = dato;
	always @(posedge clock)
		begin dato = D;
	end
endmodule

V_primo_elab/counter_12.v
module contatore(
	input CLK,
	output reg [3:0] O = 4'd0
	);
	
	parameter N = 4;
	
	reg [3:0] costante = 4'd1;
	wire [3:0] w, w2;
	
	
	registroparallelo #(N) parall(
		.D(w),
		.clock(CLK),
		.Q(w2)
	);
	
	Sommatore #(N) Sum (
		.A(costante),
		.B(w2),
		.O(w)
	);
	
	always @(posedge CLK) begin
		if(w2 < 4'd12) begin
			O <= w2;
		end else begin
			O <= 4'd0;
		end
	end
	
	
	
endmodule

V_primo_elab/S0.v
module Stato0(

	input [2:0] i1,
	input clk,
	output [2:0] O0, O1, O2, O3, O4, O5, O6, O7, O8, O9, O10, O11
	
	);
	
	wire [3:0] outcont;
	
	contatore comp1(
	
		.CLK(clk),
		.O(outcont)
	
	);
	
	wire [2:0] o0, o1, o2, o3, o4, o5, o6, o7, o8, o9, o10, o11;
	wire [15:0] outdec;
	
	demux comp2(
	
		.ctrl(outcont),
		.in(i1),
		.out0(o0),
		.out1(o1),
		.out2(o2),
		.out3(o3),
		.out4(o4),
		.out5(o5),
		.out6(o6),
		.out7(o7),
		.out8(o8),
		.out9(o9),
		.out10(o10),
		.out11(o11)
	
	);
	
	
	Decoder #(4) dec(
		.A(outcont),
		.O(outdec)	
	);
	
	
	registrope_en #(3) reg0(.D(o0), .clock(clk), .enable(outdec[0]), .Q(O0));
	registrope_en #(3) reg1(.D(o1), .clock(clk), .enable(outdec[1]), .Q(O1));
	registrope_en #(3) reg2(.D(o2), .clock(clk), .enable(outdec[2]), .Q(O2));
	registrope_en #(3) reg3(.D(o3), .clock(clk), .enable(outdec[3]), .Q(O3));
	registrope_en #(3) reg4(.D(o4), .clock(clk), .enable(outdec[4]), .Q(O4));
	registrope_en #(3) reg5(.D(o5), .clock(clk), .enable(outdec[5]), .Q(O5));
	registrope_en #(3) reg6(.D(o6), .clock(clk), .enable(outdec[6]), .Q(O6));
	registrope_en #(3) reg7(.D(o7), .clock(clk), .enable(outdec[7]), .Q(O7));	
	registrope_en #(3) reg8(.D(o8), .clock(clk), .enable(outdec[8]), .Q(O8));
	registrope_en #(3) reg9(.D(o9), .clock(clk), .enable(outdec[9]), .Q(O9));
	registrope_en #(3) reg10(.D(o10), .clock(clk), .enable(outdec[10]), .Q(O10));
	registrope_en #(3) reg11(.D(o11), .clock(clk), .enable(outdec[11]), .Q(O11));	
	
endmodule

//verilator --trace --binary tb_S0.v S0.v counter_12.v Regparallenable.v Demux_ctrl4.v reg_parallelo.v Adder1bit.v Decoder.v --top-module stato0_tb -o provaS0

V_primo_elab/tb_S0.v
module stato0_tb();

    reg [2:0] stringa;
    reg C;
    wire [2:0] out0, out1, out2, out3, out4, out5, out6, out7, out8, out9, out10, out11;
    
    Stato0 state(
        .i1(stringa),
        .clk(C),
        .O0(out0),
        .O1(out1),
        .O2(out2),
        .O3(out3),
        .O4(out4),
        .O5(out5),
        .O6(out6),
        .O7(out7),
        .O8(out8),
        .O9(out9),
        .O10(out10),
        .O11(out11)
    );  
    
    integer i;

    initial begin
        // I REGISTRI DEVONO AGGIORNARSI SUL FALLING EDGE (QUANDO C = 0)
        $dumpfile("stato0_sim.vcd");
        $dumpvars(0, stato0_tb);
        
        stringa = 3'b111;
        C = 0;

        // 20 cicli di clock
        for (i = 0; i < 12; i = i + 1) begin
            #5 C = ~C;  // fronte di salita
            #5 C = ~C;  // fronte di discesa
        end
        
        $finish;
    end
    
endmodule

V_primo_elab/stato0_sim.vcd
$version Generated by VerilatedVcd $end
$timescale 1ps $end
 $scope module TOP $end
  $scope module stato0_tb $end
   $var wire 3 K stringa [2:0] $end
   $var wire 1 L C $end
   $var wire 3 / out0 [2:0] $end
   $var wire 3 0 out1 [2:0] $end
   $var wire 3 1 out2 [2:0] $end
   $var wire 3 2 out3 [2:0] $end
   $var wire 3 3 out4 [2:0] $end
   $var wire 3 4 out5 [2:0] $end
   $var wire 3 5 out6 [2:0] $end
   $var wire 3 6 out7 [2:0] $end
   $var wire 3 7 out8 [2:0] $end
   $var wire 3 8 out9 [2:0] $end
   $var wire 3 9 out10 [2:0] $end
   $var wire 3 : out11 [2:0] $end
   $var wire 32 M i [31:0] $end
   $scope module state $end
    $var wire 3 K i1 [2:0] $end
    $var wire 1 L clk $end
    $var wire 3 / O0 [2:0] $end
    $var wire 3 0 O1 [2:0] $end
    $var wire 3 1 O2 [2:0] $end
    $var wire 3 2 O3 [2:0] $end
    $var wire 3 3 O4 [2:0] $end
    $var wire 3 4 O5 [2:0] $end
    $var wire 3 5 O6 [2:0] $end
    $var wire 3 6 O7 [2:0] $end
    $var wire 3 7 O8 [2:0] $end
    $var wire 3 8 O9 [2:0] $end
    $var wire 3 9 O10 [2:0] $end
    $var wire 3 : O11 [2:0] $end
    $var wire 4 ; outcont [3:0] $end
    $var wire 3 # o0 [2:0] $end
    $var wire 3 $ o1 [2:0] $end
    $var wire 3 % o2 [2:0] $end
    $var wire 3 & o3 [2:0] $end
    $var wire 3 ' o4 [2:0] $end
    $var wire 3 ( o5 [2:0] $end
    $var wire 3 ) o6 [2:0] $end
    $var wire 3 * o7 [2:0] $end
    $var wire 3 + o8 [2:0] $end
    $var wire 3 , o9 [2:0] $end
    $var wire 3 - o10 [2:0] $end
    $var wire 3 . o11 [2:0] $end
    $var wire 16 < outdec [15:0] $end
    $scope module comp1 $end
     $var wire 1 L CLK $end
     $var wire 4 ; O [3:0] $end
     $var wire 32 N N [31:0] $end
     $var wire 4 O costante [3:0] $end
     $var wire 4 = w [3:0] $end
     $var wire 4 > w2 [3:0] $end
     $scope module Sum $end
      $var wire 32 N N [31:0] $end
      $var wire 4 O A [3:0] $end
      $var wire 4 > B [3:0] $end
      $var wire 4 = O [3:0] $end
     $upscope $end
     $scope module parall $end
      $var wire 32 N N [31:0] $end
      $var wire 4 = D [3:0] $end
      $var wire 1 L clock $end
      $var wire 4 > Q [3:0] $end
      $var wire 4 > dato [3:0] $end
     $upscope $end
    $upscope $end
    $scope module comp2 $end
     $var wire 4 ; ctrl [3:0] $end
     $var wire 3 K in [2:0] $end
     $var wire 3 # out0 [2:0] $end
     $var wire 3 $ out1 [2:0] $end
     $var wire 3 % out2 [2:0] $end
     $var wire 3 & out3 [2:0] $end
     $var wire 3 ' out4 [2:0] $end
     $var wire 3 ( out5 [2:0] $end
     $var wire 3 ) out6 [2:0] $end
     $var wire 3 * out7 [2:0] $end
     $var wire 3 + out8 [2:0] $end
     $var wire 3 , out9 [2:0] $end
     $var wire 3 - out10 [2:0] $end
     $var wire 3 . out11 [2:0] $end
    $upscope $end
    $scope module dec $end
     $var wire 32 N N [31:0] $end
     $var wire 4 ; A [3:0] $end
     $var wire 16 < O [15:0] $end
     $var wire 32 P i [31:0] $end
    $upscope $end
    $scope module reg0 $end
     $var wire 32 Q N [31:0] $end
     $var wire 3 # D [2:0] $end
     $var wire 1 L clock $end
     $var wire 1 ? enable $end
     $var wire 3 / Q [2:0] $end
     $var wire 3 / dato [2:0] $end
    $upscope $end
    $scope module reg1 $end
     $var wire 32 Q N [31:0] $end
     $var wire 3 $ D [2:0] $end
     $var wire 1 L clock $end
     $var wire 1 @ enable $end
     $var wire 3 0 Q [2:0] $end
     $var wire 3 0 dato [2:0] $end
    $upscope $end
    $scope module reg10 $end
     $var wire 32 Q N [31:0] $end
     $var wire 3 - D [2:0] $end
     $var wire 1 L clock $end
     $var wire 1 A enable $end
     $var wire 3 9 Q [2:0] $end
     $var wire 3 9 dato [2:0] $end
    $upscope $end
    $scope module reg11 $end
     $var wire 32 Q N [31:0] $end
     $var wire 3 . D [2:0] $end
     $var wire 1 L clock $end
     $var wire 1 B enable $end
     $var wire 3 : Q [2:0] $end
     $var wire 3 : dato [2:0] $end
    $upscope $end
    $scope module reg2 $end
     $var wire 32 Q N [31:0] $end
     $var wire 3 % D [2:0] $end
     $var wire 1 L clock $end
     $var wire 1 C enable $end
     $var wire 3 1 Q [2:0] $end
     $var wire 3 1 dato [2:0] $end
    $upscope $end
    $scope module reg3 $end
     $var wire 32 Q N [31:0] $end
     $var wire 3 & D [2:0] $end
     $var wire 1 L clock $end
     $var wire 1 D enable $end
     $var wire 3 2 Q [2:0] $end
     $var wire 3 2 dato [2:0] $end
    $upscope $end
    $scope module reg4 $end
     $var wire 32 Q N [31:0] $end
     $var wire 3 ' D [2:0] $end
     $var wire 1 L clock $end
     $var wire 1 E enable $end
     $var wire 3 3 Q [2:0] $end
     $var wire 3 3 dato [2:0] $end
    $upscope $end
    $scope module reg5 $end
     $var wire 32 Q N [31:0] $end
     $var wire 3 ( D [2:0] $end
     $var wire 1 L clock $end
     $var wire 1 F enable $end
     $var wire 3 4 Q [2:0] $end
     $var wire 3 4 dato [2:0] $end
    $upscope $end
    $scope module reg6 $end
     $var wire 32 Q N [31:0] $end
     $var wire 3 ) D [2:0] $end
     $var wire 1 L clock $end
     $var wire 1 G enable $end
     $var wire 3 5 Q [2:0] $end
     $var wire 3 5 dato [2:0] $end
    $upscope $end
    $scope module reg7 $end
     $var wire 32 Q N [31:0] $end
     $var wire 3 * D [2:0] $end
     $var wire 1 L clock $end
     $var wire 1 H enable $end
     $var wire 3 6 Q [2:0] $end
     $var wire 3 6 dato [2:0] $end
    $upscope $end
    $scope module reg8 $end
     $var wire 32 Q N [31:0] $end
     $var wire 3 + D [2:0] $end
     $var wire 1 L clock $end
     $var wire 1 I enable $end
     $var wire 3 7 Q [2:0] $end
     $var wire 3 7 dato [2:0] $end
    $upscope $end
    $scope module reg9 $end
     $var wire 32 Q N [31:0] $end
     $var wire 3 , D [2:0] $end
     $var wire 1 L clock $end
     $var wire 1 J enable $end
     $var wire 3 8 Q [2:0] $end
     $var wire 3 8 dato [2:0] $end
    $upscope $end
   $upscope $end
  $upscope $end
 $upscope $end
$enddefinitions $end


#0
b111 #
b000 $
b000 %
b000 &
b000 '
b000 (
b000 )
b000 *
b000 +
b000 ,
b000 -
b000 .
b000 /
b000 0
b000 1
b000 2
b000 3
b000 4
b000 5
b000 6
b000 7
b000 8
b000 9
b000 :
b0000 ;
b0000000000000001 <
b0001 =
b0000 >
1?
0@
0A
0B
0C
0D
0E
0F
0G
0H
0I
0J
b111 K
0L
b00000000000000000000000000000000 M
b00000000000000000000000000000100 N
b0001 O
b00000000000000000000000000010000 P
b00000000000000000000000000000011 Q
#5
b000 #
b111 $
b111 /
b0001 ;
b0000000000000010 <
b0010 =
b0001 >
0?
1@
1L
#10
0L
b00000000000000000000000000000001 M
#15
b000 $
b111 %
b111 0
b0010 ;
b0000000000000100 <
b0011 =
b0010 >
0@
1C
1L
#20
0L
b00000000000000000000000000000010 M
#25
b000 %
b111 &
b111 1
b0011 ;
b0000000000001000 <
b0100 =
b0011 >
0C
1D
1L
#30
0L
b00000000000000000000000000000011 M
#35
b000 &
b111 '
b111 2
b0100 ;
b0000000000010000 <
b0101 =
b0100 >
0D
1E
1L
#40
0L
b00000000000000000000000000000100 M
#45
b000 '
b111 (
b111 3
b0101 ;
b0000000000100000 <
b0110 =
b0101 >
0E
1F
1L
#50
0L
b00000000000000000000000000000101 M
#55
b000 (
b111 )
b111 4
b0110 ;
b0000000001000000 <
b0111 =
b0110 >
0F
1G
1L
#60
0L
b00000000000000000000000000000110 M
#65
b000 )
b111 *
b111 5
b0111 ;
b0000000010000000 <
b1000 =
b0111 >
0G
1H
1L
#70
0L
b00000000000000000000000000000111 M
#75
b000 *
b111 +
b111 6
b1000 ;
b0000000100000000 <
b1001 =
b1000 >
0H
1I
1L
#80
0L
b00000000000000000000000000001000 M
#85
b000 +
b111 ,
b111 7
b1001 ;
b0000001000000000 <
b1010 =
b1001 >
0I
1J
1L
#90
0L
b00000000000000000000000000001001 M
#95
b000 ,
b111 -
b111 8
b1010 ;
b0000010000000000 <
b1011 =
b1010 >
1A
0J
1L
#100
0L
b00000000000000000000000000001010 M
#105
b000 -
b111 .
b111 9
b1011 ;
b0000100000000000 <
b1100 =
b1011 >
0A
1B
1L
#110
0L
b00000000000000000000000000001011 M
#115
b111 #
b000 .
b111 :
b0000 ;
b0000000000000001 <
b1101 =
b1100 >
1?
0B
1L
#120
0L
b00000000000000000000000000001100 M
